CQUPTSDK/GetCookie.py
CQUPTSDK/GetExam.py
CQUPTSDK/GetRoom.py
CQUPTSDK/GetSchedule.py
CQUPTSDK/GetStudentInfo.py
CQUPTSDK/GetUrl.py
CQUPTSDK/Judge.py
CQUPTSDK/Login.py
CQUPTSDK/LoginApi.py
CQUPTSDK/__init__.py
CQUPTSDK/config/url.json
CQUPTSDK-0.0.8.dist-info/LICENSE.txt
CQUPTSDK-0.0.8.dist-info/METADATA
CQUPTSDK-0.0.8.dist-info/WHEEL
CQUPTSDK-0.0.8.dist-info/top_level.txt
CQUPTSDK-0.0.8.dist-info/zip-safe
CQUPTSDK-0.0.8.dist-info/RECORD
